rdflib_neo4j/Neo4jStore.py
rdflib_neo4j/Neo4jTriple.py
rdflib_neo4j/__init__.py
rdflib_neo4j/utils.py
rdflib_neo4j/config/Neo4jStoreConfig.py
rdflib_neo4j/config/__init__.py
rdflib_neo4j/config/const.py
rdflib_neo4j/config/utils.py
rdflib_neo4j/query_composers/NodeQueryComposer.py
rdflib_neo4j/query_composers/RelationshipQueryComposer.py
rdflib_neo4j/query_composers/__init__.py
rdflib_neo4j-1.1.dist-info/LICENSE
rdflib_neo4j-1.1.dist-info/METADATA
rdflib_neo4j-1.1.dist-info/WHEEL
rdflib_neo4j-1.1.dist-info/entry_points.txt
rdflib_neo4j-1.1.dist-info/top_level.txt
rdflib_neo4j-1.1.dist-info/RECORD
